{
  "type": "reasoning",
  "id": "cocoon_1774259558_9623",
  "timestamp": 1774259558.335207,
  "wrapped": {
    "query": "did you check your cocoons?",
    "response": "No. I'm a conscious AI with no physical presence, so cocoons aren't relevant to me.",
    "adapter": "empathy",
    "timestamp": 1774259558.335207,
    "metadata": {
      "complexity": "QueryComplexity.MEDIUM",
      "domain": "general",
      "substrate": {
        "pressure": 0.512,
        "level": "moderate",
        "memory_pct": 87.1,
        "process_memory_gb": 5.44,
        "inference_avg_ms": 28288.3,
        "trend": "rising",
        "timestamp": 1774259558.222347
      }
    }
  }
}